pythonpkg/__init__.py
pypkgpy-0.9.dist-info/Licence.txt
pypkgpy-0.9.dist-info/METADATA
pypkgpy-0.9.dist-info/WHEEL
pypkgpy-0.9.dist-info/top_level.txt
pypkgpy-0.9.dist-info/RECORD
