Metadata-Version: 2.1
Name: pypkgpy
Version: 0.9
Summary: This is pypkgpy package
Author: Henil
License: UNKNOWN
Platform: UNKNOWN
License-File: Licence.txt
